{
  "person": "saram",
  "bicycle": "jajeongeo",
  "car": "jadongcha",
  "motorcycle": "otobai",
  "airplane": "bihaenggi",
  "bus": "beoseu",
  "train": "gicha",
  "truck": "teureok",
  "boat": "bae",
  "traffic light": "sinhodeung",
  "fire hydrant": "sohwajeon",
  "stop sign": "jeongji pyojipan",
  "parking meter": "jucha miteogi",
  "bench": "benchi",
  "bird": "sae",
  "cat": "goyangi",
  "dog": "gae",
  "horse": "mal",
  "sheep": "yang",
  "cow": "so",
  "elephant": "kokkiri",
  "bear": "gom",
  "zebra": "eollukmal",
  "giraffe": "girin",
  "backpack": "baenang",
  "umbrella": "usan",
  "handbag": "haendeubaek",
  "tie": "nektai",
  "suitcase": "yeohaeng gabang",
  "frisbee": "peuriseubi",
  "skis": "seuki",
  "snowboard": "seunobo deu",
  "sports ball": "gong",
  "kite": "yeon",
  "baseball bat": "yagu bangmangi",
  "baseball glove": "yagu geulleobeeu",
  "skateboard": "seukeiteubo deu",
  "surfboard": "seopingbo deu",
  "tennis racket": "teniseu raket",
  "bottle": "byeong",
  "wine glass": "wainjan",
  "cup": "keop",
  "fork": "pokeu",
  "knife": "kal",
  "spoon": "sutgarak",
  "bowl": "geureut",
  "banana": "banana",
  "apple": "sagwa",
  "sandwich": "saendeuwichi",
  "orange": "orenji",
  "broccoli": "beurokollі",
  "carrot": "danggeun",
  "hot dog": "hatdogeu",
  "pizza": "pija",
  "donut": "donut",
  "cake": "keikeu",
  "chair": "uija",
  "couch": "sopa",
  "potted plant": "hwabun",
  "bed": "chimdae",
  "dining table": "siktak",
  "toilet": "byeongi",
  "tv": "tellebijeon",
  "laptop": "noteubuk",
  "mouse": "mauseu",
  "remote": "rimokon",
  "keyboard": "kibodeu",
  "cell phone": "hyudaejeonhwa",
  "microwave": "jeonjareinjі",
  "oven": "obeun",
  "toaster": "toseuteo",
  "sink": "singkeudae",
  "refrigerator": "naengjanggo",
  "book": "chaek",
  "clock": "sigye",
  "vase": "kkotbyeong",
  "scissors": "gawi",
  "teddy bear": "tedi beeo",
  "hair drier": "heeo deuraіeo",
  "toothbrush": "chitsol"
}
